{
  "name": "Daniel Crawford",
  "age": 25,
  "address": {
    "street": "Jokwab Road",
    "city": "Atnernew",
    "state": "OR",
    "zip": "35355"
  },
  "contact": {
    "phone": "(253) 408-9041",
    "servicePhone": "800827635"
  },
  "birthday": "1999-11-06T07:02:44.735Z",
  "ip": "231.185.32.95",
  "foo": "bar",
  "profile": {
    "about": "Nidro hues visanu bo nume niuv pod fag gojregsov hireage son junacsi sisoju gem ekvur duca cenhowku. Valum umazonsel routele banenli iboca ba guvdoho tejcewgo owtacwa mu nu kal ov. Lezwiz ecaibeeki ad wis tiv mebic vepe wusdu sow tofatsow ubmiuc epcamlah. Izzope vil bured pe ogohut gorajhin udfok cajgalub jocwom en sozno licamek nihec. Omuwa rez dumeweno lim verto doijesos buwdah koboc bov nu dikni dawke jal.",
    "bio": "Ret eruzavar hesmo idasiju ino kuflud nan huhace bavwewun avesa todmoc uvi jo sijehrut taipa mogozwa. Efjikova gocwomiv keclap ip zarufimas ag gi cevjifek pezpon igteete ba zogpa raruc put tez. Wi kigep jewafil visog sobva igluze tuf adji robrid co he beserpub toigpi akat arvupzu olihu."
  },
  "apiKey": "0293544289aa819340c3b4ca9f948ca83c01b57bc8f85a711323dcd955ecfb97",
  "currency": {
    "code": "CNY",
    "name": "China Yuan Renminbi"
  }
}