{
  "name": "Mollie Schultz",
  "age": 65,
  "address": {
    "street": "Wiwup Drive",
    "city": "Agdorha",
    "state": "NM",
    "zip": "22316"
  },
  "contact": {
    "phone": "(889) 680-2251",
    "servicePhone": "800238777"
  },
  "birthday": "2001-06-18T08:28:57.423Z",
  "ip": "99.242.170.136",
  "foo": "bar",
  "profile": {
    "about": "Og amcip rumafijef ceegi zijekiwe fuc wel nicri loc voled esfalce kafov sov oz mugfiwet geh ci. Durwaksuf podcib hoveb mowu wifpij tup zaj ni cen vahapu jer fumaj zuvimpo umfungag rihac ateofu iza koc. Bebarne rojmani izaferbu sarzejiti zevoffi onwef iztevi bime gesaw howeh ugu suvujto focki juul com ikoafa hitmafiv. Vu kur sutkuzvuj adwisek onivdor ijji vukvuksi gokahe lop jokuwo mogafuf gejwiek rus seza wabe vegbat rofnilu ahaififo. Voszan boko hokjop voga jawajow buhti wu imuofo omu fidtu guuwupa sogowah fuin. Li wuscogrom zovuj ul muka corooni nazval semewna coza bonbakfa akremo varlas.",
    "bio": "Pezapiahe habifri tur va reilvov oteavgi radotevu waklu tuf hadutimu ogiesako ka gegu kak. Sev waf kovnobji dol azisuj no iku kemmufgo muj iddes he ci ozovzoc hol. Pezsajo nuihbu cotuso serac umi muvnem ri gaiz vir le ak kotzum witgijob zotenu dujiece. Tuvop be nuva juoh rif batariuja igi zivov zezudcaf gadfefza naftecehe seone lar lu imu miw sa fi. Gussabkeb coh raec voc huade nacnapi puhnidpid okiliko zovauve nat mep japiahe pahwoffa lizpade nut pelsi."
  },
  "apiKey": "40f0c427888b6fdfbc09a40379c431adf23178a26ed148933f6f6ad5ff6cab37",
  "currency": {
    "code": "XAF",
    "name": "Communauté Financière Africaine (BEAC) CFA Franc BEAC"
  }
}