{
  "name": "Sallie Ramsey",
  "age": 21,
  "address": {
    "street": "Hege Key",
    "city": "Saluwko",
    "state": "SD",
    "zip": "84150"
  },
  "contact": {
    "phone": "(655) 835-9260",
    "servicePhone": "800384769"
  },
  "birthday": "1991-07-09T09:34:51.046Z",
  "ip": "35.143.78.119",
  "foo": "bar",
  "profile": {
    "about": "Ufa gagme norur tamoz agepe ekisokigu waguhilod vulamren hefarat fo vempov cihge ra. Zor suevuroj tanupsi iruita oka delobgi bagzuf vow gas orpof ce fidi zelinu siwgevuh nis. Na boftofik talor nihar love enaguzu javojik wouknoc sa tidpiga hukig lidpiknit fusu kok vi. Wa wel epe fepeb elole cul penlu netwiufe nato je runak um keusur hotwi ac impan. Awwumhu gi famzug marud romdup ojtifi du as jiz naha te gafi li damu. Himin suckec uc maztesje ren bivpe indef hahpunu rezgagmo rafgeoz jobmewfip tiv ojonge jaahjoh zehpuot deg.",
    "bio": "Povhi zegof fogbebu ijifep zuzuv foin zektir op ve betipa tivafi ava sagzasep fuf fen giduhan huh. Upivejvu nowaho ogkepa susazi otetungo fiz janaadu uzobal obebirpe rortug soc vazur sewucsur sarih lajtu zoagreb. Lol it bopnidhos wopiz ha misepvo og fesorso ha eg kugmioso inoruk. Hajoc im gu nibapa cucfulir med hed hibopo vapnesi dadehze pidom laluh jecvip dafceji kilot todzuh fe. Ukeapmu septijra golitor wedes fidaplen ru depev toslunu lufel gal jifdaada ticsorni lenpet toc seap titiju."
  },
  "apiKey": "a8bbaa7dee68b7a640b0528a95aadca2233ef04cf552e272e4fd52db397dd76a",
  "currency": {
    "code": "MMK",
    "name": "Myanmar (Burma) Kyat"
  }
}